quangdon/__init__.py
quangdon/cutlet.py
quangdon/en.py
quangdon/espeak.py
quangdon/token.py
quangdon/data/us_gold.json
quangdon/data/us_silver.json
quangdon-0.9.6.dist-info/METADATA
quangdon-0.9.6.dist-info/WHEEL
quangdon-0.9.6.dist-info/licenses/LICENSE
quangdon-0.9.6.dist-info/RECORD
