Metadata-Version: 2.4
Name: quangdon
Version: 0.9.6
Summary: G2P engine for English TTS (US)
Author-email: mr-don88 <donson.vietmold@gmail.com>
License:                                  Apache License
License-File: LICENSE
Classifier: License :: OSI Approved :: Apache Software License
Classifier: Operating System :: OS Independent
Classifier: Programming Language :: Python :: 3
Requires-Python: <3.14,>=3.8
Requires-Dist: addict
Requires-Dist: pip>=25.0.1
Requires-Dist: regex
Provides-Extra: en
Requires-Dist: espeakng-loader; extra == 'en'
Requires-Dist: num2words; extra == 'en'
Requires-Dist: phonemizer-fork; extra == 'en'
Requires-Dist: spacy; extra == 'en'
Requires-Dist: spacy-curated-transformers; extra == 'en'
Requires-Dist: torch; extra == 'en'
Requires-Dist: transformers; extra == 'en'
